Metadata-Version: 1.0
Name: django-tagging-ext
Version: 0.3.6
Summary: Adds in new features to supplement django-tagging
Home-page: http://github.com/pydanny/django-tagging-ext
Author: Daniel Greenfeld
Author-email: pydanny@gmail.com
License: MIT
Keywords: django,pinax
Platform: UNKNOWN
Classifier: Development Status :: 4 - Beta
Classifier: Programming Language :: Python
Classifier: Topic :: Software Development :: Libraries :: Python Modules
Classifier: Framework :: Django
Classifier: Environment :: Web Environment
Classifier: Intended Audience :: Developers
Classifier: License :: OSI Approved :: BSD License
Classifier: Operating System :: OS Independent
Classifier: Topic :: Utilities
